MANIFEST.in
README.rst
setup.cfg
setup.py
versioneer.py
f_ccid/__init__.py
f_ccid/_version.py
f_ccid/iccd.py
f_ccid/slot.py
f_ccid/usb.py
usb_f_ccid.egg-info/PKG-INFO
usb_f_ccid.egg-info/SOURCES.txt
usb_f_ccid.egg-info/dependency_links.txt
usb_f_ccid.egg-info/requires.txt
usb_f_ccid.egg-info/top_level.txt