Metadata-Version: 1.1
Name: usb-f-ccid
Version: 0.2
Summary: Userland USB Gadget implementation of CCID/ICCD class.
Home-page: http://github.com/vpelletier/python-usb-f-ccid
Author: Vincent Pelletier
Author-email: plr.vincent@gmail.com
License: GPLv3+
Keywords: linux usb gadget ccid iccd
Platform: linux
Classifier: License :: OSI Approved :: GNU General Public License v3 or later (GPLv3+)
Classifier: Operating System :: POSIX :: Linux
Classifier: Programming Language :: Python :: 3
Classifier: Programming Language :: Python :: Implementation :: CPython
Classifier: Programming Language :: Python :: Implementation :: PyPy
Classifier: Topic :: System :: Hardware :: Hardware Drivers
